algorithms/__init__.py
algorithms/entity/__init__.py
algorithms/entity/node.py
algorithms/huffman/__init__.py
algorithms/huffman/compressor.py
algorithms/utils/__init__.py
algorithms/utils/tools.py
tcmpr/__init__.py
tcmpr/application.py
tcmpr/argument_parser.py
tcmpr/algorithms/__init__.py
tcmpr/algorithms/entity/__init__.py
tcmpr/algorithms/entity/node.py
tcmpr/algorithms/huffman/__init__.py
tcmpr/algorithms/huffman/compressor.py
tcmpr/algorithms/huffman/decompressor.py
tcmpr/algorithms/lzss/__init__.py
tcmpr/algorithms/lzss/compressor.py
tcmpr/algorithms/lzw/__init__.py
tcmpr/algorithms/lzw/compressor.py
tcmpr/algorithms/lzw/decompressor.py
tcmpr/algorithms/utils/__init__.py
tcmpr/algorithms/utils/tools.py
tcmpr-0.2.dist-info/AUTHORS.rst
tcmpr-0.2.dist-info/LICENSE.txt
tcmpr-0.2.dist-info/METADATA
tcmpr-0.2.dist-info/WHEEL
tcmpr-0.2.dist-info/entry_points.txt
tcmpr-0.2.dist-info/top_level.txt
tcmpr-0.2.dist-info/RECORD
