Metadata-Version: 2.1
Name: tcmpr
Version: 0.2
Summary: 'Simple program to compressing text files using 4 most popular lossless algorithms'
Home-page: https://tcmpr.readthedocs.io/en/latest/
Author: Konrad Poreba
Author-email: konrad@porebasoftware.pl
License: mit
Platform: any
Classifier: Development Status :: 4 - Beta
Classifier: Programming Language :: Python
Provides-Extra: testing
Requires-Dist: pytest ; extra == 'testing'
Requires-Dist: pytest-cov ; extra == 'testing'
